[
  {
    "ts": "2025-08-10T07:27:55.168377+00:00",
    "type": "start",
    "data": {
      "phase": "INIT"
    }
  },
  {
    "ts": "2025-08-10T07:27:55.170655+00:00",
    "type": "parse",
    "data": {
      "phase": "INIT"
    }
  },
  {
    "ts": "2025-08-10T07:27:55.177338+00:00",
    "type": "jam",
    "data": {
      "phase": "JAM",
      "mode": "implication-jam",
      "details": {
        "mode": "implication-jam",
        "is_contradiction": true,
        "witness": {
          "pattern": "1 -> 0",
          "node": [
            "->",
            1,
            0
          ],
          "antecedent": 1,
          "consequent": 0
        },
        "witness_hash": "cb9cb8a99390b8e3",
        "ast_size": 3,
        "depth": 2
      }
    }
  },
  {
    "ts": "2025-08-10T07:27:55.179531+00:00",
    "type": "alive",
    "data": {
      "phase": "JAM"
    }
  },
  {
    "ts": "2025-08-10T07:27:55.181578+00:00",
    "type": "phase",
    "data": {
      "phase": "JAM"
    }
  },
  {
    "ts": "2025-08-10T07:27:55.213875+00:00",
    "type": "mem",
    "data": {
      "phase": "MEM",
      "time_to_mem_ms": 43.371
    }
  },
  {
    "ts": "2025-08-10T07:27:55.217637+00:00",
    "type": "end",
    "data": {
      "phase": "MEM"
    }
  }
]